radicale_auth_sh/__init__.py
radicale_auth_sh/cli.py
radicale_auth_sh/config.py
radicale_auth_sh/crypt.py
radicale_auth_sh-0.1.0.dist-info/LICENSE
radicale_auth_sh-0.1.0.dist-info/WHEEL
radicale_auth_sh-0.1.0.dist-info/METADATA
radicale_auth_sh-0.1.0.dist-info/RECORD
