Metadata-Version: 2.1
Name: radicale-auth-sh
Version: 0.1.0
Summary: Plugin radicale-auth-sh
Home-page: https://codeberg.org/ashwinvis/radicale-auth-sh
Keywords: authentication, radicale, argon2, caldav, carddav
Author: Ashwin V. Mohanan
Author-email: y4d71nsar@relay.firefox.com
Requires-Python: >=3.6
Classifier: License :: OSI Approved :: Apache Software License
Requires-Dist: argon2-cffi < 21.0.0
Requires-Dist: radicale >= 3.0.0
Requires-Dist: setuptools
Requires-Dist: scriv[toml] ; extra == "dev"
Requires-Dist: build ; extra == "dev"
Requires-Dist: pytest ; extra == "test"
Requires-Dist: pytest-cov ; extra == "test"
Provides-Extra: dev
Provides-Extra: test
